reporting_api_client/VERSION
reporting_api_client/__init__.py
reporting_api_client/client.py
reporting_api_client/oauth/__init__.py
reporting_api_client/oauth/transport.py
jampp_reporting_api_client-0.3.0.dist-info/METADATA
jampp_reporting_api_client-0.3.0.dist-info/WHEEL
jampp_reporting_api_client-0.3.0.dist-info/top_level.txt
jampp_reporting_api_client-0.3.0.dist-info/RECORD
